[{"strDataType":"text","strName":"中文名","strValue":"花斑連鰭䲗","strThumbnailUrl":null},{"strDataType":"text","strName":"學名","strValue":"Synchiropus splendidus","strThumbnailUrl":null},{"strDataType":"text","strName":"中英文科名","strValue":"鼠科 (Callionymidae)","strThumbnailUrl":null},{"strDataType":"text","strName":"英文俗名","strValue":"Mandarinfish","strThumbnailUrl":null},{"strDataType":"text","strName":"最大體長","strValue":"6 cm","strThumbnailUrl":null},{"strDataType":"text","strName":"臺灣分布","strValue":"蘭嶼、東沙","strThumbnailUrl":null},{"strDataType":"text","strName":"世界分布","strValue":"西太平洋","strThumbnailUrl":null},{"strDataType":"text","strName":"棲所生態","strValue":"主要棲息於水淺且有遮蔽的潟湖與近海岩礁區，通常棲息的是淤泥底的珊瑚與碎石的水域。通常形成小的群，散佈於小的區域。","strThumbnailUrl":null},{"strDataType":"text","strName":"形態特徵","strValue":"體延長，頭部稍縱扁。枕骨區平滑。鰓孔下側位。前鰓蓋骨強棘末端向上彎曲，強棘腹緣及基部平滑無棘，背緣具二至五彎曲棘突。側線從眼延伸至尾鰭基部，無橫向側線，將體兩側側線相連。第一背鰭極低，雄魚第I棘延長成絲狀；第二背鰭鰭緣稍凸；通常背鰭與臀鰭鰭條均分支；尾鰭圓形。新鮮標本體呈紅褐色，具許多藍綠色的波狀長條班，頭部背面深橄欖綠色，腹面淡綠；前鰓蓋骨區具一大型深藍班，其上具許多不規則的黃點及黃線。各鰭鰭緣深藍色，通常具波狀的橙線；背鰭紅褐色；胸鰭淡藍色；腹鰭具藍點；臀鰭鰭膜具深色垂線，鰭條橄欖綠色；尾鰭紅褐色。","strThumbnailUrl":null},{"strDataType":"image","strName":"2030.\t鰭連鰭 Pterosynchiropus splendidus (Herre, 1927)","strValue":"http://image.nmmba.gov.tw/upload/archive/23192/preview_20161017161238.jpg","strThumbnailUrl":"http://image.nmmba.gov.tw/upload/archive/23192/thumbnail_20161017161238.jpg"}]